planet/__about__.py
planet/__init__.py
planet/admin.py
planet/apps.py
planet/context_processors.py
planet/forms.py
planet/managers.py
planet/models.py
planet/settings.py
planet/tasks.py
planet/urls.py
planet/utils.py
planet/views.py
planet/locale/es/LC_MESSAGES/django.mo
planet/locale/es/LC_MESSAGES/django.po
planet/management/__init__.py
planet/management/commands/__init__.py
planet/management/commands/planet_add_feed.py
planet/management/commands/planet_update_all_feeds.py
planet/migrations/0001_initial.py
planet/migrations/__init__.py
planet/static/planet/planet.css
planet/static/planet/images/wavegrid.png
planet/templates/base.html
planet/templates/planet/base.html
planet/templates/planet/authors/detail.html
planet/templates/planet/authors/list.html
planet/templates/planet/authors/blocks/list.html
planet/templates/planet/authors/blocks/list_for_feed.html
planet/templates/planet/blogs/detail.html
planet/templates/planet/blogs/list.html
planet/templates/planet/blogs/blocks/list.html
planet/templates/planet/feeds/detail.html
planet/templates/planet/feeds/list.html
planet/templates/planet/feeds/blocks/list_for_author.html
planet/templates/planet/posts/detail.html
planet/templates/planet/posts/details.html
planet/templates/planet/posts/full_details.html
planet/templates/planet/posts/list.html
planet/templates/planet/posts/blocks/list.html
planet/templatetags/__init__.py
planet/templatetags/planet_tags.py
django_planet-1.0.0a2.dist-info/METADATA
django_planet-1.0.0a2.dist-info/WHEEL
django_planet-1.0.0a2.dist-info/licenses/AUTHORS.md
django_planet-1.0.0a2.dist-info/licenses/LICENSE
django_planet-1.0.0a2.dist-info/RECORD
