Metadata-Version: 2.4
Name: django-planet
Version: 1.0.0a2
Summary: A django planet and feeds (RSS and ATOM) aggregator application for Django.
Project-URL: Homepage, https://github.com/matagus/django-planet
Project-URL: Issues, https://.github.com/matagus/django-planet/issues
Project-URL: Repository, https://github.com/matagus/django-planet
Project-URL: Changelog, https://githib.com/matagus/django-planet/releases
Project-URL: Pypi, https://pypi.org/project/django-planet
Author-email: Matias Agustin Mendez <matagus@gmail.com>
License-Expression: BSD-3-Clause
License-File: AUTHORS.md
License-File: LICENSE
Classifier: Development Status :: 5 - Production/Stable
Classifier: Environment :: Console
Classifier: Environment :: Web Environment
Classifier: Framework :: Django
Classifier: Framework :: Django :: 4.0
Classifier: Framework :: Django :: 4.1
Classifier: Framework :: Django :: 4.2
Classifier: Framework :: Django :: 5.0
Classifier: Framework :: Django :: 5.1
Classifier: Framework :: Django :: 5.2
Classifier: Intended Audience :: Developers
Classifier: License :: OSI Approved :: BSD License
Classifier: Natural Language :: English
Classifier: Programming Language :: Python
Classifier: Programming Language :: Python :: 3.9
Classifier: Programming Language :: Python :: 3.10
Classifier: Programming Language :: Python :: 3.11
Classifier: Programming Language :: Python :: 3.12
Classifier: Programming Language :: Python :: Implementation :: CPython
Classifier: Programming Language :: Python :: Implementation :: PyPy
Classifier: Topic :: Internet :: WWW/HTTP :: Dynamic Content :: News/Diary
Classifier: Topic :: Software Development :: Libraries
Requires-Dist: django-pagination-py3>=2.1.0
Requires-Dist: django>=4.0
Requires-Dist: feedparser>=6.0
Provides-Extra: docs
Requires-Dist: mkdocs; extra == 'docs'
Requires-Dist: mkdocs-material; extra == 'docs'
Requires-Dist: pygments; extra == 'docs'
Requires-Dist: pymdown-extensions; extra == 'docs'
